README.rst
setup.py
vector/__init__.py
vector/core.py
vectotools.egg-info/PKG-INFO
vectotools.egg-info/SOURCES.txt
vectotools.egg-info/dependency_links.txt
vectotools.egg-info/top_level.txt